chemic/__init__.py
chemic/common_formulas.csv
chemic/main.py
chemic/periodic_table.csv
chemic/run.py
chemic/utils.py
chemic-1.2.0.dist-info/METADATA
chemic-1.2.0.dist-info/WHEEL
chemic-1.2.0.dist-info/RECORD
