Metadata-Version: 2.1
Name: chemic
Version: 1.2.0
Summary: 
Author: uncenter
Author-email: me@uncenter.org
Requires-Python: >=3.11,<4.0
Classifier: Programming Language :: Python :: 3
Classifier: Programming Language :: Python :: 3.11
Requires-Dist: commoner (>=0.4.2,<0.5.0)
Requires-Dist: nicegui (>=1.1.11,<2.0.0)
Requires-Dist: pandas (>=1.5.3,<2.0.0)
Requires-Dist: pydash (>=6.0.2,<7.0.0)
